ccl_localstorage.py
ccl_localstorage-1.0.dist-info/LICENSE
ccl_localstorage-1.0.dist-info/METADATA
ccl_localstorage-1.0.dist-info/WHEEL
ccl_localstorage-1.0.dist-info/RECORD
